{"name": "GUEDJ Thierry", "summary": {"matches": 9, "wins": 3, "losses": 6, "perfs": 1, "contres": 0, "win_rate": 0.3333333333333333, "diff_sets_total": -9, "dominance": -1.0, "clutch_played": 0, "clutch_wins": 0, "clutch_rate": null, "clutch_index": null, "opp_pts_mean": 725.2233333333334, "pointres_total": 8.5, "pointres_mean": 0.9444444444444444, "std_points_fftt": 4.329770615199714, "dispersion_perf_contre": 0.31426968052735454, "expected_wins": 2.677893627571312, "overperf": 0.3221063724286881}, "segments": {"equipe": {"p2_s7": {"phase": 2, "segment_id": 7, "segment_nom": "Mars", "matches": 3, "wins": 1, "losses": 2, "perfs": 0, "contres": 0, "win_rate": 0.3333333333333333, "diff_sets": -3, "pointres_total": 4.0, "pointres_mean": 1.3333333333333333, "opp_pts_mean": 804.96, "expected_wins": 0.7300205544704582, "overperf": 0.2699794455295418}, "p2_s8": {"phase": 2, "segment_id": 8, "segment_nom": "Avril", "matches": 2, "wins": 0, "losses": 2, "perfs": 0, "contres": 0, "win_rate": 0.0, "diff_sets": -6, "pointres_total": -8.0, "pointres_mean": -4.0, "opp_pts_mean": 666.94, "expected_wins": 0.679964380353669, "overperf": -0.679964380353669}}, "indiv": {"p2_s6": {"phase": 2, "segment_id": 6, "segment_nom": "Février", "matches": 4, "wins": 2, "losses": 2, "perfs": 1, "contres": 0, "win_rate": 0.5, "diff_sets": 0, "pointres_total": 12.5, "pointres_mean": 3.125, "opp_pts_mean": 694.5625, "expected_wins": 1.2679086927471848, "overperf": 0.7320913072528152}}, "tous": {"p2_s6": {"phase": 2, "segment_id": 6, "segment_nom": "Février", "matches": 4, "wins": 2, "losses": 2, "perfs": 1, "contres": 0, "win_rate": 0.5, "diff_sets": 0, "pointres_total": 12.5, "pointres_mean": 3.125, "opp_pts_mean": 694.5625, "expected_wins": 1.2679086927471848, "overperf": 0.7320913072528152}, "p2_s7": {"phase": 2, "segment_id": 7, "segment_nom": "Mars", "matches": 3, "wins": 1, "losses": 2, "perfs": 0, "contres": 0, "win_rate": 0.3333333333333333, "diff_sets": -3, "pointres_total": 4.0, "pointres_mean": 1.3333333333333333, "opp_pts_mean": 804.96, "expected_wins": 0.7300205544704582, "overperf": 0.2699794455295418}, "p2_s8": {"phase": 2, "segment_id": 8, "segment_nom": "Avril", "matches": 2, "wins": 0, "losses": 2, "perfs": 0, "contres": 0, "win_rate": 0.0, "diff_sets": -6, "pointres_total": -8.0, "pointres_mean": -4.0, "opp_pts_mean": 666.94, "expected_wins": 0.679964380353669, "overperf": -0.679964380353669}}}, "timeline": {"equipe": [{"date": "20/03/2026", "match_id": 12503822.0, "phase": 2, "segment_id": 7, "segment_nom": "Mars", "opp_name": "ROYER Patrick", "diff_pts": -258.5, "pts_start": 589.5, "opp_pts_start": 848.0, "win": false, "pointres": -1.0, "pointres_cum": -1.0, "points_est": 588.5, "expected_p": 0.08706577244027125, "expected_cum": 0.08706577244027125, "real_cum": 0, "overperf_cum": -0.08706577244027125, "perfs_cum": 0, "contres_cum": 0, "perf": 0, "contre": 0, "sets_for": 0, "sets_against": 3, "close_match": false}, {"date": "20/03/2026", "match_id": 12503826.0, "phase": 2, "segment_id": 7, "segment_nom": "Mars", "opp_name": "RISI Vincent", "diff_pts": 56.5, "pts_start": 589.5, "opp_pts_start": 533.0, "win": true, "pointres": 5.0, "pointres_cum": 4.0, "points_est": 593.5, "expected_p": 0.6256585353521225, "expected_cum": 0.7127243077923937, "real_cum": 1, "overperf_cum": 0.2872756922076063, "perfs_cum": 0, "contres_cum": 0, "perf": 0, "contre": 0, "sets_for": 3, "sets_against": 0, "close_match": false}, {"date": "20/03/2026", "match_id": 12503832.0, "phase": 2, "segment_id": 7, "segment_nom": "Mars", "opp_name": "DAUPHANT Jean-Paul", "diff_pts": -444.3800000000001, "pts_start": 589.5, "opp_pts_start": 1033.88, "win": false, "pointres": 0.0, "pointres_cum": 4.0, "points_est": 593.5, "expected_p": 0.01729624667806455, "expected_cum": 0.7300205544704582, "real_cum": 1, "overperf_cum": 0.26997944552954173, "perfs_cum": 0, "contres_cum": 0, "perf": 0, "contre": 0, "sets_for": 0, "sets_against": 3, "close_match": false}, {"date": "10/04/2026", "match_id": null, "phase": 2, "segment_id": 8, "segment_nom": "Avril", "opp_name": "DEGORGUE Olivier", "diff_pts": -91.38, "pts_start": 593.5, "opp_pts_start": 684.88, "win": false, "pointres": -4.0, "pointres_cum": 0.0, "points_est": 589.5, "expected_p": 0.30349131414601255, "expected_cum": 1.0335118686164708, "real_cum": 1, "overperf_cum": -0.03351186861647082, "perfs_cum": 0, "contres_cum": 0, "perf": 0, "contre": 0, "sets_for": 0, "sets_against": 3, "close_match": false}, {"date": "10/04/2026", "match_id": null, "phase": 2, "segment_id": 8, "segment_nom": "Avril", "opp_name": "ELMALEH Tom", "diff_pts": -55.5, "pts_start": 593.5, "opp_pts_start": 649.0, "win": false, "pointres": -4.0, "pointres_cum": -4.0, "points_est": 585.5, "expected_p": 0.3764730662076564, "expected_cum": 1.4099849348241271, "real_cum": 1, "overperf_cum": -0.40998493482412723, "perfs_cum": 0, "contres_cum": 0, "perf": 0, "contre": 0, "sets_for": 0, "sets_against": 3, "close_match": false}], "indiv": [{"date": "15/02/2026", "match_id": 12185761.0, "phase": 2, "segment_id": 6, "segment_nom": "Février", "opp_name": "FUMEE Arnaud", "diff_pts": -28.0, "pts_start": 577.0, "opp_pts_start": 605.0, "win": true, "pointres": 8.75, "pointres_cum": 8.75, "points_est": 585.75, "expected_p": 0.4367050258582008, "expected_cum": 0.4367050258582008, "real_cum": 1, "overperf_cum": 0.5632949741417992, "perfs_cum": 1, "contres_cum": 0, "perf": 1, "contre": 0, "sets_for": 0, "sets_against": 0, "close_match": false}, {"date": "15/02/2026", "match_id": 12185762.0, "phase": 2, "segment_id": 6, "segment_nom": "Février", "opp_name": "NGUYEN Linh", "diff_pts": -254.75, "pts_start": 577.0, "opp_pts_start": 831.75, "win": false, "pointres": -1.25, "pointres_cum": 7.5, "points_est": 584.5, "expected_p": 0.08981391973704787, "expected_cum": 0.5265189455952487, "real_cum": 1, "overperf_cum": 0.4734810544047513, "perfs_cum": 1, "contres_cum": 0, "perf": 0, "contre": 0, "sets_for": 0, "sets_against": 0, "close_match": false}, {"date": "15/02/2026", "match_id": 12185765.0, "phase": 2, "segment_id": 6, "segment_nom": "Février", "opp_name": "YVON Mathieu", "diff_pts": -257.25, "pts_start": 577.0, "opp_pts_start": 834.25, "win": false, "pointres": -1.25, "pointres_cum": 6.25, "points_est": 583.25, "expected_p": 0.08797326333112532, "expected_cum": 0.614492208926374, "real_cum": 1, "overperf_cum": 0.385507791073626, "perfs_cum": 1, "contres_cum": 0, "perf": 0, "contre": 0, "sets_for": 0, "sets_against": 0, "close_match": false}, {"date": "15/02/2026", "match_id": 12185767.0, "phase": 2, "segment_id": 6, "segment_nom": "Février", "opp_name": "HAIRAULT Raphaël", "diff_pts": 69.75, "pts_start": 577.0, "opp_pts_start": 507.25, "win": true, "pointres": 6.25, "pointres_cum": 12.5, "points_est": 589.5, "expected_p": 0.6534164838208106, "expected_cum": 1.2679086927471848, "real_cum": 2, "overperf_cum": 0.7320913072528153, "perfs_cum": 1, "contres_cum": 0, "perf": 0, "contre": 0, "sets_for": 0, "sets_against": 0, "close_match": false}], "tous": [{"date": "15/02/2026", "match_id": 12185761.0, "phase": 2, "segment_id": 6, "segment_nom": "Février", "opp_name": "FUMEE Arnaud", "diff_pts": -28.0, "pts_start": 577.0, "opp_pts_start": 605.0, "win": true, "pointres": 8.75, "pointres_cum": 8.75, "points_est": 585.75, "expected_p": 0.4367050258582008, "expected_cum": 0.4367050258582008, "real_cum": 1, "overperf_cum": 0.5632949741417992, "perfs_cum": 1, "contres_cum": 0, "perf": 1, "contre": 0, "sets_for": 0, "sets_against": 0, "close_match": false}, {"date": "15/02/2026", "match_id": 12185762.0, "phase": 2, "segment_id": 6, "segment_nom": "Février", "opp_name": "NGUYEN Linh", "diff_pts": -254.75, "pts_start": 577.0, "opp_pts_start": 831.75, "win": false, "pointres": -1.25, "pointres_cum": 7.5, "points_est": 584.5, "expected_p": 0.08981391973704787, "expected_cum": 0.5265189455952487, "real_cum": 1, "overperf_cum": 0.4734810544047513, "perfs_cum": 1, "contres_cum": 0, "perf": 0, "contre": 0, "sets_for": 0, "sets_against": 0, "close_match": false}, {"date": "15/02/2026", "match_id": 12185765.0, "phase": 2, "segment_id": 6, "segment_nom": "Février", "opp_name": "YVON Mathieu", "diff_pts": -257.25, "pts_start": 577.0, "opp_pts_start": 834.25, "win": false, "pointres": -1.25, "pointres_cum": 6.25, "points_est": 583.25, "expected_p": 0.08797326333112532, "expected_cum": 0.614492208926374, "real_cum": 1, "overperf_cum": 0.385507791073626, "perfs_cum": 1, "contres_cum": 0, "perf": 0, "contre": 0, "sets_for": 0, "sets_against": 0, "close_match": false}, {"date": "15/02/2026", "match_id": 12185767.0, "phase": 2, "segment_id": 6, "segment_nom": "Février", "opp_name": "HAIRAULT Raphaël", "diff_pts": 69.75, "pts_start": 577.0, "opp_pts_start": 507.25, "win": true, "pointres": 6.25, "pointres_cum": 12.5, "points_est": 589.5, "expected_p": 0.6534164838208106, "expected_cum": 1.2679086927471848, "real_cum": 2, "overperf_cum": 0.7320913072528153, "perfs_cum": 1, "contres_cum": 0, "perf": 0, "contre": 0, "sets_for": 0, "sets_against": 0, "close_match": false}, {"date": "20/03/2026", "match_id": 12503822.0, "phase": 2, "segment_id": 7, "segment_nom": "Mars", "opp_name": "ROYER Patrick", "diff_pts": -258.5, "pts_start": 589.5, "opp_pts_start": 848.0, "win": false, "pointres": -1.0, "pointres_cum": 11.5, "points_est": 588.5, "expected_p": 0.08706577244027125, "expected_cum": 1.354974465187456, "real_cum": 2, "overperf_cum": 0.6450255348125441, "perfs_cum": 1, "contres_cum": 0, "perf": 0, "contre": 0, "sets_for": 0, "sets_against": 3, "close_match": false}, {"date": "20/03/2026", "match_id": 12503826.0, "phase": 2, "segment_id": 7, "segment_nom": "Mars", "opp_name": "RISI Vincent", "diff_pts": 56.5, "pts_start": 589.5, "opp_pts_start": 533.0, "win": true, "pointres": 5.0, "pointres_cum": 16.5, "points_est": 593.5, "expected_p": 0.6256585353521225, "expected_cum": 1.9806330005395785, "real_cum": 3, "overperf_cum": 1.0193669994604218, "perfs_cum": 1, "contres_cum": 0, "perf": 0, "contre": 0, "sets_for": 3, "sets_against": 0, "close_match": false}, {"date": "20/03/2026", "match_id": 12503832.0, "phase": 2, "segment_id": 7, "segment_nom": "Mars", "opp_name": "DAUPHANT Jean-Paul", "diff_pts": -444.3800000000001, "pts_start": 589.5, "opp_pts_start": 1033.88, "win": false, "pointres": 0.0, "pointres_cum": 16.5, "points_est": 593.5, "expected_p": 0.01729624667806455, "expected_cum": 1.997929247217643, "real_cum": 3, "overperf_cum": 1.0020707527823571, "perfs_cum": 1, "contres_cum": 0, "perf": 0, "contre": 0, "sets_for": 0, "sets_against": 3, "close_match": false}, {"date": "10/04/2026", "match_id": null, "phase": 2, "segment_id": 8, "segment_nom": "Avril", "opp_name": "DEGORGUE Olivier", "diff_pts": -91.38, "pts_start": 593.5, "opp_pts_start": 684.88, "win": false, "pointres": -4.0, "pointres_cum": 12.5, "points_est": 589.5, "expected_p": 0.30349131414601255, "expected_cum": 2.301420561363656, "real_cum": 3, "overperf_cum": 0.6985794386363446, "perfs_cum": 1, "contres_cum": 0, "perf": 0, "contre": 0, "sets_for": 0, "sets_against": 3, "close_match": false}, {"date": "10/04/2026", "match_id": null, "phase": 2, "segment_id": 8, "segment_nom": "Avril", "opp_name": "ELMALEH Tom", "diff_pts": -55.5, "pts_start": 593.5, "opp_pts_start": 649.0, "win": false, "pointres": -4.0, "pointres_cum": 8.5, "points_est": 585.5, "expected_p": 0.3764730662076564, "expected_cum": 2.6778936275713123, "real_cum": 3, "overperf_cum": 0.3221063724286882, "perfs_cum": 1, "contres_cum": 0, "perf": 0, "contre": 0, "sets_for": 0, "sets_against": 3, "close_match": false}]}, "pts_actuel_last": 585.5, "radar": {"all": {"raw": {"win_rate": 0.3333333333333333, "perf_rate": 0.1111111111111111, "strength": 34.7027876984127, "anti_contre": 1.0, "clutch_rate": 0.0, "dominance": -1.0}, "norm": {"win_rate": 0.39166666666666666, "perf_rate": 0.3333333333333333, "strength": 0.47798895630777094, "anti_contre": 1.0, "clutch_rate": 0.0, "dominance": 0.42391304347826086}}, "p1": {}, "p2": {"raw": {"win_rate": 0.3333333333333333, "perf_rate": 0.1111111111111111, "strength": 34.7027876984127, "anti_contre": 1.0, "clutch_rate": 0.0, "dominance": -1.0}, "norm": {"win_rate": 0.3939393939393939, "perf_rate": 0.2222222222222222, "strength": 0.323608949351786, "anti_contre": 1.0, "clutch_rate": 0.0, "dominance": 0.4044943820224719}}}, "opp_brackets": [{"label": "< -200", "V": 0, "D": 4, "n": 4, "win_rate": 0.0}, {"label": "-100 → 0", "V": 1, "D": 2, "n": 3, "win_rate": 0.3333}, {"label": "0 → +100", "V": 2, "D": 0, "n": 2, "win_rate": 1.0}], "season": "2025-2026"}